santodigital_bigquery/__init__.py
santodigital_bigquery/io/__init__.py
santodigital_bigquery/io/bigquery.py
santodigital_bigquery-1.0.1.dist-info/LICENSE
santodigital_bigquery-1.0.1.dist-info/METADATA
santodigital_bigquery-1.0.1.dist-info/WHEEL
santodigital_bigquery-1.0.1.dist-info/top_level.txt
santodigital_bigquery-1.0.1.dist-info/RECORD
